{
  "text_blocks": [
    {
      "text": "1974",
      "bounding_box": [
        {
          "x": 5,
          "y": 288
        },
        {
          "x": 40,
          "y": 288
        },
        {
          "x": 40,
          "y": 300
        },
        {
          "x": 5,
          "y": 300
        }
      ],
      "confidence": 0.99208785
    },
    {
      "text": "100",
      "bounding_box": [
        {
          "x": 60,
          "y": 62
        },
        {
          "x": 85,
          "y": 62
        },
        {
          "x": 85,
          "y": 75
        },
        {
          "x": 60,
          "y": 75
        }
      ],
      "confidence": 0.9865617533333334
    },
    {
      "text": "443",
      "bounding_box": [
        {
          "x": 57,
          "y": 130
        },
        {
          "x": 85,
          "y": 130
        },
        {
          "x": 85,
          "y": 141
        },
        {
          "x": 57,
          "y": 141
        }
      ],
      "confidence": 0.98566568
    },
    {
      "text": "444",
      "bounding_box": [
        {
          "x": 57,
          "y": 236
        },
        {
          "x": 84,
          "y": 236
        },
        {
          "x": 84,
          "y": 246
        },
        {
          "x": 57,
          "y": 246
        }
      ],
      "confidence": 0.9860155233333333
    },
    {
      "text": "440",
      "bounding_box": [
        {
          "x": 181,
          "y": 7
        },
        {
          "x": 209,
          "y": 7
        },
        {
          "x": 209,
          "y": 18
        },
        {
          "x": 181,
          "y": 18
        }
      ],
      "confidence": 0.9874057133333333
    },
    {
      "text": "440",
      "bounding_box": [
        {
          "x": 289,
          "y": 7
        },
        {
          "x": 315,
          "y": 7
        },
        {
          "x": 315,
          "y": 18
        },
        {
          "x": 289,
          "y": 18
        }
      ],
      "confidence": 0.9910735
    },
    {
      "text": "444",
      "bounding_box": [
        {
          "x": 58,
          "y": 343
        },
        {
          "x": 86,
          "y": 343
        },
        {
          "x": 86,
          "y": 353
        },
        {
          "x": 58,
          "y": 353
        }
      ],
      "confidence": 0.9859639533333334
    },
    {
      "text": "200",
      "bounding_box": [
        {
          "x": 276,
          "y": 372
        },
        {
          "x": 302,
          "y": 372
        },
        {
          "x": 302,
          "y": 384
        },
        {
          "x": 276,
          "y": 384
        }
      ],
      "confidence": 0.9907378033333334
    },
    {
      "text": "100",
      "bounding_box": [
        {
          "x": 408,
          "y": 63
        },
        {
          "x": 434,
          "y": 63
        },
        {
          "x": 434,
          "y": 76
        },
        {
          "x": 408,
          "y": 76
        }
      ],
      "confidence": 0.9851967133333334
    },
    {
      "text": "443",
      "bounding_box": [
        {
          "x": 406,
          "y": 128
        },
        {
          "x": 432,
          "y": 128
        },
        {
          "x": 432,
          "y": 140
        },
        {
          "x": 406,
          "y": 140
        }
      ],
      "confidence": 0.9905166733333334
    },
    {
      "text": "444",
      "bounding_box": [
        {
          "x": 406,
          "y": 235
        },
        {
          "x": 432,
          "y": 235
        },
        {
          "x": 432,
          "y": 246
        },
        {
          "x": 406,
          "y": 246
        }
      ],
      "confidence": 0.98958098
    },
    {
      "text": "444",
      "bounding_box": [
        {
          "x": 406,
          "y": 343
        },
        {
          "x": 433,
          "y": 343
        },
        {
          "x": 433,
          "y": 353
        },
        {
          "x": 406,
          "y": 353
        }
      ],
      "confidence": 0.9904139066666667
    },
    {
      "text": "444",
      "bounding_box": [
        {
          "x": 406,
          "y": 450
        },
        {
          "x": 432,
          "y": 450
        },
        {
          "x": 432,
          "y": 460
        },
        {
          "x": 406,
          "y": 460
        }
      ],
      "confidence": 0.98971007
    },
    {
      "text": "444",
      "bounding_box": [
        {
          "x": 58,
          "y": 450
        },
        {
          "x": 85,
          "y": 450
        },
        {
          "x": 85,
          "y": 460
        },
        {
          "x": 58,
          "y": 460
        }
      ],
      "confidence": 0.9885127066666667
    },
    {
      "text": "544",
      "bounding_box": [
        {
          "x": 276,
          "y": 460
        },
        {
          "x": 302,
          "y": 460
        },
        {
          "x": 302,
          "y": 471
        },
        {
          "x": 276,
          "y": 471
        }
      ],
      "confidence": 0.8674343866666666
    },
    {
      "text": "100",
      "bounding_box": [
        {
          "x": 60,
          "y": 515
        },
        {
          "x": 85,
          "y": 515
        },
        {
          "x": 85,
          "y": 527
        },
        {
          "x": 60,
          "y": 527
        }
      ],
      "confidence": 0.9841972600000001
    },
    {
      "text": "100",
      "bounding_box": [
        {
          "x": 408,
          "y": 515
        },
        {
          "x": 434,
          "y": 515
        },
        {
          "x": 434,
          "y": 527
        },
        {
          "x": 408,
          "y": 527
        }
      ],
      "confidence": 0.9899390166666667
    }
  ],
  "frames": [
    {
      "x": 250,
      "y": 58,
      "w": 100,
      "h": 468,
      "area": 46800,
      "aspect": 4.68,
      "fill_ratio": 0.950910785262681,
      "h_lines_count": 2,
      "v_lines_count": 3,
      "total_lines": 5
    },
    {
      "x": 149,
      "y": 60,
      "w": 96,
      "h": 466,
      "area": 44736,
      "aspect": 4.854166666666667,
      "fill_ratio": 0.9767735150294837,
      "h_lines_count": 2,
      "v_lines_count": 3,
      "total_lines": 5
    }
  ],
  "panels": [
    {
      "outer_width": 440.0,
      "outer_height": 1974.0,
      "inner_heights": [
        100.0,
        443.0,
        444.0,
        444.0,
        444.0,
        100.0
      ]
    },
    {
      "outer_width": 440.0,
      "outer_height": 1974.0,
      "inner_heights": [
        100.0,
        443.0,
        444.0,
        444.0,
        444.0,
        100.0
      ]
    }
  ],
  "quality_scores": {
    "overall": 0.75,
    "consistency": 1.0,
    "frequency": 1.0,
    "inner_sum": 0.0,
    "completeness": 1.0
  }
}